jlx_helper
