Metadata-Version: 2.1
Name: JLX-helper
Version: 0.0.5
Summary: This is my JLX help package
Home-page: https://github.com/ckf10000/JLX-helper
Author: ckf10000
Author-email: ckf10000@sina.com
Classifier: Programming Language :: Python :: 3
Classifier: License :: OSI Approved :: MIT License
Classifier: Operating System :: OS Independent
License-File: LICENSE
Requires-Dist: requests>=2.31.0
